phruzz_matcher/__init__.py
phruzz_matcher/phrase_matcher.py
phruzz_matcher-0.0.4.dist-info/LICENSE
phruzz_matcher-0.0.4.dist-info/METADATA
phruzz_matcher-0.0.4.dist-info/WHEEL
phruzz_matcher-0.0.4.dist-info/top_level.txt
phruzz_matcher-0.0.4.dist-info/RECORD
