Metadata-Version: 2.1
Name: phruzz-matcher
Version: 0.0.4
Summary: Combination of the RapidFuzz library with Spacy PhraseMatcher 
Home-page: https://github.com/mjvallone/phruzz-matcher
Author: Martin Vallone
Author-email: mjvallone@gmail.com
License: UNKNOWN
Project-URL: Phruzz Matcher, https://github.com/mjvallone/phruzz-matcher
Platform: UNKNOWN
Classifier: Programming Language :: Python :: 3
Classifier: Programming Language :: Python :: 3.7
Classifier: License :: OSI Approved :: MIT License
Classifier: Operating System :: OS Independent
Classifier: Intended Audience :: Developers
Classifier: Intended Audience :: Science/Research
Classifier: Topic :: Scientific/Engineering
Requires-Python: >=3.7
License-File: LICENSE
Requires-Dist: setuptools (>=54)
Requires-Dist: wheel
Requires-Dist: rapidfuzz
